labeltransform2/__init__.py
labeltransform2/format.py
labeltransform2/generate_voc.py
labeltransform2/tools.py
labeltransform2/xml/voc.xml
labeltransform2-2.2.dist-info/LICENSE
labeltransform2-2.2.dist-info/METADATA
labeltransform2-2.2.dist-info/WHEEL
labeltransform2-2.2.dist-info/top_level.txt
labeltransform2-2.2.dist-info/RECORD
