Metadata-Version: 2.1
Name: labeltransform2
Version: 2.2
Summary: dataset label style transform tool
Home-page: https://gitee.com/free_bigD/labeltransform.git
Author: victor
Requires-Python: >=3
License-File: LICENSE
Requires-Dist: opencv-python
Requires-Dist: pandas
Requires-Dist: scikit-learn
